{
  "value": [
    {
      "code": "DVN",
      "url": "/upcom/DVN-tong-cong-ty-duoc-viet-nam-ctcp.chn",
      "company": "Tổng Công ty Dược Việt Nam - CTCP",
      "price": 21,
      "stock_exchange": "Upcom",
      "branch": "DOANH NGHIEP THONG THUONG",
      "data": {
        "2011": {
          "quarter": {
            "q1": {},
            "q2": {},
            "q3": {},
            "q4": {}
          },
          "bvps": null,
          "eps": null,
          "roe": null,
          "roa": null
        },
        "2012": {
          "quarter": {
            "q1": {},
            "q2": {},
            "q3": {},
            "q4": {}
          },
          "bvps": null,
          "eps": null,
          "roe": null,
          "roa": null
        },
        "2013": {
          "quarter": {
            "q1": {},
            "q2": {},
            "q3": {},
            "q4": {}
          },
          "bvps": 47617.02,
          "eps": 6993.17,
          "roe": 14.69,
          "roa": 6.02,
          "doanh_so": 8092962336,
          "loi_nhuan_sau_thue": 311381141,
          "tai_san": 5110214784,
          "no_dai_han": 153402773,
          "von_chu_so_huu": 2093010319,
          "roic": 13.861259182868046,
          "effectiveness": 1.583683402376537,
          "effciency": 3.8475545550839936
        },
        "2014": {
          "quarter": {
            "q1": {},
            "q2": {},
            "q3": {},
            "q4": {}
          },
          "bvps": 52106.93,
          "eps": 8578.61,
          "roe": 17.2,
          "roa": 6.99,
          "doanh_so": 8085846948,
          "loi_nhuan_sau_thue": 384611865,
          "tai_san": 5676050421,
          "no_dai_han": 144636309,
          "von_chu_so_huu": 2290364341,
          "roic": 15.795144243595994,
          "effectiveness": 1.4245551656983775,
          "effciency": 4.756605801141612
        },
        "2015": {
          "quarter": {
            "q1": {},
            "q2": {},
            "q3": {},
            "q4": {}
          },
          "bvps": 77659.35,
          "eps": 7714.58,
          "roe": 11.99,
          "roa": 5.56,
          "luu_chuyen_tien_te": 178934507,
          "doanh_so": 7380800481,
          "loi_nhuan_sau_thue": 350017342,
          "tai_san": 6785214006,
          "no_dai_han": 84434262,
          "von_chu_so_huu": 3488258265,
          "roic": 9.797018337145026,
          "effectiveness": 1.0877771098263573,
          "effciency": 4.742268035845583,
          "productitivty": 0.5112161185430635
        },
        "2016": {
          "quarter": {
            "q1": {},
            "q2": {
              "doanh_so": 84545350,
              "loi_nhuan_sau_thue": 29453424,
              "effciency": 34.837426304344355
            },
            "q3": {},
            "q4": {
              "bvps": 8904.92,
              "eps": 2707.32,
              "roe": 28.34,
              "roa": 10.17
            }
          },
          "bvps": 9554.18,
          "eps": 2707.32,
          "roe": 22.31,
          "roa": 9.8,
          "luu_chuyen_tien_te": -62225987,
          "doanh_so": 6122122113,
          "loi_nhuan_sau_thue": 661836317,
          "tai_san": 6308017402,
          "no_dai_han": 55150344,
          "von_chu_so_huu": 2264340969,
          "roic": 28.533683799142555,
          "effectiveness": 0.9705303144945255,
          "effciency": 10.810570334665913,
          "productitivty": -0.09402020620757201
        },
        "2017": {
          "quarter": {
            "q1": {
              "bvps": null,
              "eps": null,
              "roe": null,
              "roa": null,
              "luu_chuyen_tien_te": -773943677,
              "doanh_so": 1377292550,
              "loi_nhuan_sau_thue": 54002957,
              "tai_san": 6601278953,
              "no_dai_han": 55147773,
              "von_chu_so_huu": 2955272008,
              "roic": 1.7938679961125328,
              "effectiveness": 0.2086402589265038,
              "effciency": 3.920950345661857,
              "productitivty": -14.331505532187803
            },
            "q2": {
              "luu_chuyen_tien_te": 108062817,
              "doanh_so": 2010588427,
              "loi_nhuan_sau_thue": 78907621,
              "tai_san": 6159722415,
              "no_dai_han": 49910244,
              "von_chu_so_huu": 2397259417,
              "roic": 3.224444232761351,
              "effectiveness": 0.32640893396492443,
              "effciency": 3.9246033618992877,
              "productitivty": 1.3694851730481141
            },
            "q3": {
              "luu_chuyen_tien_te": 89223910,
              "doanh_so": 1595926426,
              "loi_nhuan_sau_thue": 56126637,
              "tai_san": 6155449187,
              "no_dai_han": 53803867,
              "von_chu_so_huu": 2459056522,
              "roic": 2.2335756194690846,
              "effectiveness": 0.25927050610222185,
              "effciency": 3.516868703068897,
              "productitivty": 1.5896892236746698
            },
            "q4": {
              "luu_chuyen_tien_te": -298628236,
              "doanh_so": 1858208158,
              "loi_nhuan_sau_thue": 66640415,
              "tai_san": 6397531784,
              "no_dai_han": 47303867,
              "von_chu_so_huu": 2542209600,
              "roic": 2.5734724244243523,
              "effectiveness": 0.2904570419872415,
              "effciency": 3.5862728679291482,
              "productitivty": -4.481188119851895,
              "bvps": 9922.82,
              "eps": 904.97,
              "roe": 8.99,
              "roa": 3.45
            }
          },
          "bvps": 10574.24,
          "eps": 904.97,
          "roe": 8.99,
          "roa": 3.45,
          "luu_chuyen_tien_te": -821028870,
          "doanh_so": 6848404681,
          "loi_nhuan_sau_thue": 243016348,
          "tai_san": 6114491442,
          "no_dai_han": 60226260,
          "von_chu_so_huu": 2506095900,
          "roic": 9.469440422865693,
          "effectiveness": 1.1200285004830988,
          "effciency": 3.5485103366367494,
          "productitivty": -3.3784923391244446
        },
        "2018": {
          "quarter": {
            "q1": {
              "bvps": 9853.86,
              "eps": 906.65,
              "roe": 8.69,
              "roa": 3.44,
              "luu_chuyen_tien_te": -146220458,
              "doanh_so": 1370271882,
              "loi_nhuan_sau_thue": 38059092,
              "tai_san": 6252150500,
              "no_dai_han": 60226260,
              "von_chu_so_huu": 2495279349,
              "roic": 1.489297924683209,
              "effectiveness": 0.2191680897636741,
              "effciency": 2.777484709417689,
              "productitivty": -3.841932382412066
            },
            "q2": {
              "bvps": 10177.64,
              "eps": 892.54,
              "roe": 8.4,
              "roa": 3.38,
              "luu_chuyen_tien_te": 51034382,
              "doanh_so": 1499243909,
              "loi_nhuan_sau_thue": 72893126,
              "tai_san": 6230099763,
              "no_dai_han": 58524260,
              "von_chu_so_huu": 2572799969,
              "roic": 2.770206924583447,
              "effectiveness": 0.2406452490382055,
              "effciency": 4.861992472500351,
              "productitivty": 0.7001261271193117
            },
            "q3": {
              "bvps": 10432.16,
              "eps": 929.04,
              "roe": 8.6,
              "roa": 3.55,
              "luu_chuyen_tien_te": 21699867,
              "doanh_so": 1445972541,
              "loi_nhuan_sau_thue": 63254928,
              "tai_san": 5962026722,
              "no_dai_han": 58066160,
              "von_chu_so_huu": 2636586807,
              "roic": 2.347423908557053,
              "effectiveness": 0.24253036902104647,
              "effciency": 4.374559419797447,
              "productitivty": 0.3430541727910907
            },
            "q4": {
              "luu_chuyen_tien_te": 275008337,
              "doanh_so": 1663577667,
              "loi_nhuan_sau_thue": 40415314,
              "tai_san": 5885054100,
              "no_dai_han": 56992730,
              "von_chu_so_huu": 2668470313,
              "roic": 1.4828788122371175,
              "effectiveness": 0.2826783983175278,
              "effciency": 2.429421529376662,
              "productitivty": 6.804557722847335,
              "bvps": 10530.13,
              "eps": 788.7,
              "roe": 7.24,
              "roa": 3.16
            }
          },
          "bvps": 11227.91,
          "eps": 788.7,
          "roe": 7.24,
          "roa": 3.16,
          "luu_chuyen_tien_te": 215677459,
          "doanh_so": 6048683975,
          "loi_nhuan_sau_thue": 206318235,
          "tai_san": 5713589474,
          "no_dai_han": 56578080,
          "von_chu_so_huu": 2661014581,
          "roic": 7.591948490326011,
          "effectiveness": 1.0586486835508335,
          "effciency": 3.4109607288583796,
          "productitivty": 1.0453630480117282
        },
        "2019": {
          "quarter": {
            "q1": {
              "bvps": 10758.52,
              "eps": 926.51,
              "roe": 8.29,
              "roa": 3.69,
              "luu_chuyen_tien_te": -212803848,
              "doanh_so": 1285717795,
              "loi_nhuan_sau_thue": 61410010,
              "tai_san": 5696092405,
              "no_dai_han": 57726330,
              "von_chu_so_huu": 2719796645,
              "roic": 2.2109631694405696,
              "effectiveness": 0.22571926569720036,
              "effciency": 4.77632107440809,
              "productitivty": -3.465295771813097
            },
            "q2": {
              "bvps": 10672.48,
              "eps": 866.93,
              "roe": 7.67,
              "roa": 3.55,
              "luu_chuyen_tien_te": 153476638,
              "doanh_so": 1472967832,
              "loi_nhuan_sau_thue": 59047697,
              "tai_san": 5603870351,
              "no_dai_han": 54766410,
              "von_chu_so_huu": 2692763670,
              "roic": 2.149119219106056,
              "effectiveness": 0.2628483065703245,
              "effciency": 4.008756723480164,
              "productitivty": 2.5991976960591705
            },
            "q3": {
              "bvps": 10863.34,
              "eps": 806.41,
              "roe": 7.06,
              "roa": 3.35,
              "luu_chuyen_tien_te": 125853427,
              "doanh_so": 1431891763,
              "loi_nhuan_sau_thue": 50126073,
              "tai_san": 5629540321,
              "no_dai_han": 57676973,
              "von_chu_so_huu": 2741592843,
              "roic": 1.7906838673960823,
              "effectiveness": 0.25435322981142566,
              "effciency": 3.5006886899732796,
              "productitivty": 2.510737815028917
            },
            "q4": {
              "luu_chuyen_tien_te": 281247548,
              "doanh_so": 1596237537,
              "loi_nhuan_sau_thue": 50722207,
              "tai_san": 5636804464,
              "no_dai_han": 66137706,
              "von_chu_so_huu": 2772851628,
              "roic": 1.7866290088710843,
              "effectiveness": 0.28318128599182857,
              "effciency": 3.177610213034352,
              "productitivty": 5.544860222663418,
              "bvps": 11904.54,
              "eps": 873.14,
              "roe": 7.55,
              "roa": 3.62
            }
          },
          "bvps": 11904.54,
          "eps": 873.14,
          "roe": 7.55,
          "roa": 3.62,
          "luu_chuyen_tien_te": 177887545,
          "doanh_so": 5723375718,
          "loi_nhuan_sau_thue": 228681119,
          "tai_san": 5709444257,
          "no_dai_han": 67909403,
          "von_chu_so_huu": 2821375171,
          "roic": 7.9148008146323905,
          "effectiveness": 1.0024400730391438,
          "effciency": 3.995563637047251,
          "productitivty": 0.7778847059078804
        },
        "2020": {
          "quarter": {
            "q1": {
              "bvps": 12003.1,
              "eps": 701.03,
              "roe": 6.01,
              "roa": 2.93,
              "luu_chuyen_tien_te": -22076564,
              "doanh_so": 1329679207,
              "loi_nhuan_sau_thue": 28134393,
              "tai_san": 5793336668,
              "no_dai_han": 68310530,
              "von_chu_so_huu": 2844734796,
              "roic": 0.965806908285642,
              "effectiveness": 0.2295187183483741,
              "effciency": 2.1158782397956233,
              "productitivty": -0.7846824347694297
            },
            "q2": {
              "bvps": 11880.68,
              "eps": 786.9,
              "roe": 6.68,
              "roa": 3.24,
              "luu_chuyen_tien_te": -18441452,
              "doanh_so": 1206031622,
              "loi_nhuan_sau_thue": 79042630,
              "tai_san": 5940329466,
              "no_dai_han": 80768315,
              "von_chu_so_huu": 2815721623,
              "roic": 2.7289109125847064,
              "effectiveness": 0.20302436571958313,
              "effciency": 6.553943408956487,
              "productitivty": -0.2333102023553619
            },
            "q3": {
              "bvps": 12053.98,
              "eps": 721.72,
              "roe": 6.06,
              "roa": 2.94,
              "luu_chuyen_tien_te": 66790768,
              "doanh_so": 1281602471,
              "loi_nhuan_sau_thue": 35558550,
              "tai_san": 5874648702,
              "no_dai_han": 67335533,
              "von_chu_so_huu": 2856793713,
              "roic": 1.2160389301752499,
              "effectiveness": 0.21815814630135819,
              "effciency": 2.7745381898534123,
              "productitivty": 1.8783321592134663
            },
            "q4": {
              "luu_chuyen_tien_te": -80072923,
              "doanh_so": 1524519663,
              "loi_nhuan_sau_thue": 71019728,
              "tai_san": 6063456860,
              "no_dai_han": 67752843,
              "von_chu_so_huu": 2907957984,
              "roic": 2.386647497989562,
              "effectiveness": 0.25142747746044,
              "effciency": 4.658498655258079,
              "productitivty": -1.127474368812001,
              "bvps": 12273.91,
              "eps": 823.08,
              "roe": 6.81,
              "roa": 3.3
            }
          },
          "bvps": 12273.91,
          "eps": 823.08,
          "roe": 6.81,
          "roa": 3.3,
          "luu_chuyen_tien_te": -19160656,
          "doanh_so": 5334174801,
          "loi_nhuan_sau_thue": 215875139,
          "tai_san": 6103135625,
          "no_dai_han": 57280107,
          "von_chu_so_huu": 2908916671,
          "roic": 7.277842812086016,
          "effectiveness": 0.874005614286181,
          "effciency": 4.047020336857536,
          "productitivty": -0.08875804823453988
        },
        "2021": {
          "quarter": {
            "q1": {
              "bvps": 12498.8,
              "eps": 886.86,
              "roe": 7.28,
              "roa": 3.53,
              "doanh_so": 1011421988,
              "loi_nhuan_sau_thue": 45741546,
              "tai_san": 5951840415,
              "no_dai_han": 57115217,
              "von_chu_so_huu": 2962216170,
              "roic": 1.5149561322398826,
              "effectiveness": 0.16993432576770456,
              "effciency": 4.522498674410863
            },
            "q2": {},
            "q3": {},
            "q4": {}
          }
        }
      }
    }
  ]
}