{
  "value": [
    {
      "code": "SGP",
      "url": "/upcom/SGP-cong-ty-co-phan-cang-sai-gon.chn",
      "company": "Công ty Cổ phần Cảng Sài Gòn",
      "price": 22,
      "stock_exchange": "Upcom",
      "branch": "DOANH NGHIEP THONG THUONG",
      "data": {
        "2011": {
          "quarter": {
            "q1": {},
            "q2": {},
            "q3": {},
            "q4": {}
          },
          "bvps": 10146.98,
          "eps": 493.07,
          "roe": 4.86,
          "roa": 1.69,
          "doanh_so": 1036286055,
          "loi_nhuan_sau_thue": 51923401,
          "tai_san": 2932325265,
          "no_dai_han": 1305540696,
          "von_chu_so_huu": 1019024130,
          "roic": 2.2336826411224378,
          "effectiveness": 0.35340078652563806,
          "effciency": 5.010527812226519
        },
        "2012": {
          "quarter": {
            "q1": {},
            "q2": {},
            "q3": {},
            "q4": {}
          },
          "bvps": 10225.88,
          "eps": 442.62,
          "roe": 4.38,
          "roa": 1.57,
          "doanh_so": 926635762,
          "loi_nhuan_sau_thue": 50045289,
          "tai_san": 2819802120,
          "no_dai_han": 1173215067,
          "von_chu_so_huu": 1042804208,
          "roic": 2.2583417736743288,
          "effectiveness": 0.32861730098990066,
          "effciency": 5.4007508723799935
        },
        "2013": {
          "quarter": {
            "q1": {},
            "q2": {},
            "q3": {},
            "q4": {}
          },
          "bvps": 16984.04,
          "eps": 234.82,
          "roe": 1.87,
          "roa": 0.86,
          "doanh_so": 941945509,
          "loi_nhuan_sau_thue": 34379499,
          "tai_san": 4130456183,
          "no_dai_han": 1509646661,
          "von_chu_so_huu": 2169968478,
          "roic": 0.9343232295033777,
          "effectiveness": 0.22804878378248614,
          "effciency": 3.6498394728266605
        },
        "2014": {
          "quarter": {
            "q1": {},
            "q2": {},
            "q3": {},
            "q4": {
              "bvps": 17539.29,
              "eps": 477.36,
              "roe": 2.78,
              "roa": 1.45
            }
          },
          "bvps": 18554.94,
          "eps": 481.65,
          "roe": 2.7,
          "roa": 1.45,
          "doanh_so": 1072971260,
          "loi_nhuan_sau_thue": 65389772,
          "tai_san": 4255171053,
          "no_dai_han": 1529375675,
          "von_chu_so_huu": 2349553224,
          "roic": 1.6857687702617516,
          "effectiveness": 0.25215702180609845,
          "effciency": 6.094270595840563
        },
        "2015": {
          "quarter": {
            "q1": {},
            "q2": {},
            "q3": {
              "tai_san": 4407888838,
              "no_dai_han": 1493524297,
              "von_chu_so_huu": 2339637146
            },
            "q4": {
              "luu_chuyen_tien_te": 145057831,
              "doanh_so": 335150570,
              "loi_nhuan_sau_thue": 49303712,
              "tai_san": 3194061919,
              "no_dai_han": 1465681112,
              "von_chu_so_huu": 1305841785,
              "roic": 1.7789393713242703,
              "effectiveness": 0.10492926514866352,
              "effciency": 14.710913963237479,
              "productitivty": 2.942127988253704,
              "bvps": 5441.33,
              "eps": 446.93,
              "roe": 5.3,
              "roa": 2.54
            }
          },
          "bvps": 6037.32,
          "eps": 446.93,
          "roe": 5.29,
          "roa": 2.6,
          "luu_chuyen_tien_te": 425668037,
          "doanh_so": 1126350147,
          "loi_nhuan_sau_thue": 102017750,
          "tai_san": 3194061919,
          "no_dai_han": 1465681112,
          "von_chu_so_huu": 1305841785,
          "roic": 3.680927554682223,
          "effectiveness": 0.35263879522806457,
          "effciency": 9.057374411653537,
          "productitivty": 4.172489953954091
        },
        "2016": {
          "quarter": {
            "q1": {
              "luu_chuyen_tien_te": 29861195,
              "doanh_so": 244773804,
              "loi_nhuan_sau_thue": 17106825,
              "tai_san": 3189004128,
              "no_dai_han": 1463988656,
              "von_chu_so_huu": 1246958972,
              "roic": 0.6310274984035951,
              "effectiveness": 0.07675556197963003,
              "effciency": 6.988829981169063,
              "productitivty": 1.7455720158474761
            },
            "q2": {
              "luu_chuyen_tien_te": 159181474,
              "doanh_so": 291214342,
              "loi_nhuan_sau_thue": -1311969,
              "tai_san": 3249916742,
              "no_dai_han": 1412309223,
              "von_chu_so_huu": 1319517737,
              "roic": -0.0480253332004601,
              "effectiveness": 0.08960670845394846,
              "effciency": -0.45051661638285656,
              "productitivty": -121.3302097839202
            },
            "q3": {
              "bvps": 5648.89,
              "eps": 418.75,
              "roe": 6.93,
              "roa": 2.8,
              "luu_chuyen_tien_te": 87820942,
              "doanh_so": 278783691,
              "loi_nhuan_sau_thue": 31934615,
              "tai_san": 3312158045,
              "no_dai_han": 1421714259,
              "von_chu_so_huu": 1354969675,
              "roic": 1.1500990303205318,
              "effectiveness": 0.0841698032558709,
              "effciency": 11.454979624328168,
              "productitivty": 2.7500235089729435
            },
            "q4": {
              "luu_chuyen_tien_te": 190406086,
              "doanh_so": 431822251,
              "loi_nhuan_sau_thue": 11782889,
              "tai_san": 3409357332,
              "no_dai_han": 1398278585,
              "von_chu_so_huu": 1357153709,
              "roic": 0.42762397122431345,
              "effectiveness": 0.12665796188241848,
              "effciency": 2.728643318567667,
              "productitivty": 16.159541687951062,
              "bvps": 5812.77,
              "eps": 85.91,
              "roe": 1.38,
              "roa": 0.56
            }
          },
          "bvps": 6429.6,
          "eps": 85.91,
          "roe": 1.38,
          "roa": 0.56,
          "luu_chuyen_tien_te": 534680901,
          "doanh_so": 1202018355,
          "loi_nhuan_sau_thue": 26893142,
          "tai_san": 3442186639,
          "no_dai_han": 1407823375,
          "von_chu_so_huu": 1390691059,
          "roic": 0.9609792135880048,
          "effectiveness": 0.3492019698702921,
          "effciency": 2.237332058044987,
          "productitivty": 19.88168214037616
        },
        "2017": {
          "quarter": {
            "q1": {
              "bvps": 7147.8,
              "eps": 1489.87,
              "roe": 22.56,
              "roa": 9.39,
              "luu_chuyen_tien_te": 76150258,
              "doanh_so": 290270537,
              "loi_nhuan_sau_thue": 290430762,
              "effciency": 100.05519850607504,
              "productitivty": 0.2621976318059586
            },
            "q2": {
              "bvps": 7391.95,
              "eps": 1738.35,
              "roe": 24.55,
              "roa": 10.4,
              "luu_chuyen_tien_te": 324883963,
              "doanh_so": 299669859,
              "loi_nhuan_sau_thue": 53083410,
              "tai_san": 3980105557,
              "no_dai_han": 1393636001,
              "von_chu_so_huu": 1733355606,
              "roic": 1.6975872234888285,
              "effectiveness": 0.07529193753993696,
              "effciency": 17.713963685617113,
              "productitivty": 6.120254199946839
            },
            "q3": {
              "bvps": 7561.33,
              "eps": 1674.48,
              "roe": 22.14,
              "roa": 9.48,
              "luu_chuyen_tien_te": 429661844,
              "doanh_so": 280244187,
              "loi_nhuan_sau_thue": 18353242,
              "tai_san": 4128155744,
              "no_dai_han": 1403350952,
              "von_chu_so_huu": 1772649086,
              "roic": 0.5778728520279697,
              "effectiveness": 0.06788604994065844,
              "effciency": 6.5490179105838155,
              "productitivty": 23.410678287792425
            },
            "q4": {
              "luu_chuyen_tien_te": 253533210,
              "doanh_so": 290690663,
              "loi_nhuan_sau_thue": 68998260,
              "tai_san": 4387069201,
              "no_dai_han": 1373008095,
              "von_chu_so_huu": 1756031532,
              "roic": 2.205093837886381,
              "effectiveness": 0.06626078816667383,
              "effciency": 23.7359739346014,
              "productitivty": 3.6744870088028305,
              "bvps": 7422.79,
              "eps": 1902.02,
              "roe": 26.17,
              "roa": 10.51
            }
          },
          "bvps": 8103.55,
          "eps": 1902.02,
          "roe": 26.17,
          "roa": 10.51,
          "luu_chuyen_tien_te": 997927972,
          "doanh_so": 1160875246,
          "loi_nhuan_sau_thue": 432746868,
          "tai_san": 4386374444,
          "no_dai_han": 1372084095,
          "von_chu_so_huu": 1752757847,
          "roic": 13.848600218257054,
          "effectiveness": 0.264654844409813,
          "effciency": 37.27763766960365,
          "productitivty": 2.3060316452712026
        },
        "2018": {
          "quarter": {
            "q1": {
              "bvps": 7566.72,
              "eps": 701.94,
              "roe": 8.62,
              "roa": 3.59,
              "luu_chuyen_tien_te": 99749573,
              "doanh_so": 238044892,
              "loi_nhuan_sau_thue": 32958940,
              "tai_san": 4411909543,
              "no_dai_han": 1381902967,
              "von_chu_so_huu": 1784983402,
              "roic": 1.0407364256143918,
              "effectiveness": 0.053955070855359104,
              "effciency": 13.845682519413188,
              "productitivty": 3.0264800081556023
            },
            "q2": {
              "bvps": 7845.19,
              "eps": 785.17,
              "roe": 9.49,
              "roa": 3.91,
              "luu_chuyen_tien_te": -64001327,
              "doanh_so": 287316120,
              "loi_nhuan_sau_thue": 71243270,
              "tai_san": 4455611853,
              "no_dai_han": 1371594474,
              "von_chu_so_huu": 1847488461,
              "roic": 2.2131542255527505,
              "effectiveness": 0.06448409993490517,
              "effciency": 24.796126997677682,
              "productitivty": -0.8983490931845212
            },
            "q3": {
              "bvps": 7946.46,
              "eps": 814.98,
              "roe": 9.71,
              "roa": 3.96,
              "luu_chuyen_tien_te": 640234682,
              "doanh_so": 258413513,
              "loi_nhuan_sau_thue": 23647417,
              "tai_san": 4558381069,
              "no_dai_han": 1383547033,
              "von_chu_so_huu": 1870909943,
              "roic": 0.7266163656299016,
              "effectiveness": 0.05668975653601724,
              "effciency": 9.150998616701596,
              "productitivty": 27.074190893660816
            },
            "q4": {
              "luu_chuyen_tien_te": 176783778,
              "doanh_so": 294732519,
              "loi_nhuan_sau_thue": 59625875,
              "tai_san": 4584970985,
              "no_dai_han": 1361810699,
              "von_chu_so_huu": 1864505111,
              "roic": 1.848110306349706,
              "effectiveness": 0.06428230842991911,
              "effciency": 20.230504323820476,
              "productitivty": 2.9648835845176276,
              "bvps": 8071.61,
              "eps": 814.2,
              "roe": 9.65,
              "roa": 3.91
            }
          },
          "bvps": 8769.9,
          "eps": 814.2,
          "roe": 9.65,
          "roa": 3.91,
          "luu_chuyen_tien_te": 413699888,
          "doanh_so": 1078507045,
          "loi_nhuan_sau_thue": 181528406,
          "tai_san": 4613753538,
          "no_dai_han": 2211810699,
          "von_chu_so_huu": 1896886258,
          "roic": 4.418150277321608,
          "effectiveness": 0.23375913691902978,
          "effciency": 16.83145296468601,
          "productitivty": 2.2789815495873413
        },
        "2019": {
          "quarter": {
            "q1": {
              "luu_chuyen_tien_te": 250059631,
              "doanh_so": 289127026,
              "loi_nhuan_sau_thue": 38221050,
              "tai_san": 4644616989,
              "no_dai_han": 2224837599,
              "von_chu_so_huu": 1919437909,
              "roic": 0.9222613198909941,
              "effectiveness": 0.06224991784785464,
              "effciency": 13.219466380842585,
              "productitivty": 6.542458435861914
            },
            "q2": {
              "bvps": 8449.25,
              "eps": 909.32,
              "roe": 10.3,
              "roa": 4.25,
              "luu_chuyen_tien_te": -115915949,
              "doanh_so": 320139786,
              "loi_nhuan_sau_thue": 84946099,
              "tai_san": 4710985013,
              "no_dai_han": 2202544557,
              "von_chu_so_huu": 1988434334,
              "roic": 2.0268796672400136,
              "effectiveness": 0.06795601877666173,
              "effciency": 26.53406502870593,
              "productitivty": -1.364582368873702
            },
            "q3": {
              "bvps": 8575.57,
              "eps": 905.46,
              "roe": 10.07,
              "roa": 4.21,
              "luu_chuyen_tien_te": 78701802,
              "doanh_so": 233252229,
              "loi_nhuan_sau_thue": 20047376,
              "tai_san": 4665608501,
              "no_dai_han": 2207965175,
              "von_chu_so_huu": 2009470499,
              "roic": 0.47534515164249547,
              "effectiveness": 0.049993956618950355,
              "effciency": 8.594720010156902,
              "productitivty": 3.9257906870205854
            },
            "q4": {
              "luu_chuyen_tien_te": 290591475,
              "doanh_so": 281537076,
              "loi_nhuan_sau_thue": 11296644,
              "tai_san": 4566123640,
              "no_dai_han": 2188168198,
              "von_chu_so_huu": 1985757702,
              "roic": 0.27064792884799416,
              "effectiveness": 0.061657786384426504,
              "effciency": 4.012488927035671,
              "productitivty": 25.723699445605263,
              "bvps": 9419.64,
              "eps": 939.29,
              "roe": 10.33,
              "roa": 4.35
            }
          },
          "bvps": 9419.64,
          "eps": 939.22,
          "roe": 10.33,
          "roa": 4.35,
          "luu_chuyen_tien_te": 257960710,
          "doanh_so": 1121312835,
          "loi_nhuan_sau_thue": 206231777,
          "tai_san": 4735950849,
          "no_dai_han": 2201436071,
          "von_chu_so_huu": 2037419926,
          "roic": 4.865269713006483,
          "effectiveness": 0.23676614702130327,
          "effciency": 18.391992900001007,
          "productitivty": 1.2508291096187374
        },
        "2020": {
          "quarter": {
            "q1": {
              "bvps": 9540.23,
              "eps": 612.3,
              "roe": 6.58,
              "roa": 2.83,
              "luu_chuyen_tien_te": 263125543,
              "doanh_so": 243816923,
              "loi_nhuan_sau_thue": 20801256,
              "tai_san": 4744952786,
              "no_dai_han": 2228031366,
              "von_chu_so_huu": 2063504259,
              "roic": 0.4847042601446423,
              "effectiveness": 0.0513844782016341,
              "effciency": 8.531506240032403,
              "productitivty": 12.649502655031984
            },
            "q2": {
              "bvps": 9833.14,
              "eps": 557.86,
              "roe": 5.9,
              "roa": 2.57,
              "luu_chuyen_tien_te": -169746420,
              "doanh_so": 234806524,
              "loi_nhuan_sau_thue": 71931918,
              "tai_san": 4771992509,
              "no_dai_han": 2287002723,
              "von_chu_so_huu": 2126859136,
              "roic": 1.6296821309286926,
              "effectiveness": 0.0492051325640503,
              "effciency": 30.6345482973037,
              "productitivty": -2.359820573670787
            },
            "q3": {
              "bvps": 9954.2,
              "eps": 612.94,
              "roe": 6.37,
              "roa": 2.8,
              "luu_chuyen_tien_te": 62411381,
              "doanh_so": 215160723,
              "loi_nhuan_sau_thue": 30063671,
              "tai_san": 4825229615,
              "no_dai_han": 2306776292,
              "von_chu_so_huu": 2153043309,
              "roic": 0.6741006069675777,
              "effectiveness": 0.04459077394599801,
              "effciency": 13.972657546795844,
              "productitivty": 2.075973389942965
            },
            "q4": {
              "luu_chuyen_tien_te": 19679197,
              "doanh_so": 242110734,
              "loi_nhuan_sau_thue": 110009128,
              "tai_san": 4902593445,
              "no_dai_han": 2266297054,
              "von_chu_so_huu": 2261611665,
              "roic": 2.429579190463358,
              "effectiveness": 0.049384216071785655,
              "effciency": 45.437526119763035,
              "productitivty": 0.1788869465450176,
              "bvps": 10457.65,
              "eps": 1064.07,
              "roe": 10.71,
              "roa": 4.78
            }
          },
          "bvps": 10457.65,
          "eps": 1063.99,
          "roe": 10.71,
          "roa": 4.78,
          "luu_chuyen_tien_te": 109342354,
          "doanh_so": 935894904,
          "loi_nhuan_sau_thue": 233130990,
          "tai_san": 4902187548,
          "no_dai_han": 2266270054,
          "von_chu_so_huu": 2261936681,
          "roic": 5.148417544588984,
          "effectiveness": 0.1909137287866164,
          "effciency": 24.909953992013616,
          "productitivty": 0.4690168132516402
        },
        "2021": {
          "quarter": {
            "q1": {
              "bvps": 10889.6,
              "eps": 1411.86,
              "roe": 13.73,
              "roa": 6.26,
              "luu_chuyen_tien_te": 260626106,
              "doanh_so": 317068360,
              "loi_nhuan_sau_thue": 97367555,
              "tai_san": 5026325258,
              "no_dai_han": 2266808391,
              "von_chu_so_huu": 2355186412,
              "roic": 2.106613251421261,
              "effectiveness": 0.06308154441365442,
              "effciency": 30.708694806381814,
              "productitivty": 2.6767243564861007
            },
            "q2": {},
            "q3": {},
            "q4": {}
          }
        }
      }
    }
  ]
}