{
  "value": [
    {
      "code": "TL4",
      "url": "/upcom/TL4-tong-cong-ty-xay-dung-thuy-loi-4-ctcp.chn",
      "company": "Tổng công ty Xây dựng Thủy lợi 4 - CTCP",
      "price": 9,
      "stock_exchange": "Upcom",
      "branch": "DOANH NGHIEP THONG THUONG",
      "data": {
        "2011": {
          "quarter": {
            "q1": {},
            "q2": {},
            "q3": {},
            "q4": {}
          },
          "bvps": 14975.67,
          "eps": 2130.15,
          "roe": 15.49,
          "roa": 1.61,
          "doanh_so": 1018014603,
          "loi_nhuan_sau_thue": 30535555,
          "tai_san": 1785423577,
          "no_dai_han": 387891298,
          "von_chu_so_huu": 202168074,
          "roic": 5.174997034027281,
          "effectiveness": 0.570181001368058,
          "effciency": 2.999520332028086
        },
        "2012": {
          "quarter": {
            "q1": {},
            "q2": {},
            "q3": {},
            "q4": {
              "bvps": 14804.65,
              "eps": 1558.06,
              "roe": 10.33,
              "roa": 1.23
            }
          },
          "bvps": 14447.8,
          "eps": 1480.68,
          "roe": 10.33,
          "roa": 1.23,
          "doanh_so": 781472843,
          "loi_nhuan_sau_thue": 21437724,
          "tai_san": 1647149072,
          "no_dai_han": 432448729,
          "von_chu_so_huu": 205235154,
          "roic": 3.361810541477963,
          "effectiveness": 0.47443965836748503,
          "effciency": 2.7432461910899697
        },
        "2013": {
          "quarter": {
            "q1": {},
            "q2": {
              "tai_san": 1737233356,
              "no_dai_han": 456792453,
              "von_chu_so_huu": 210304343
            },
            "q3": {},
            "q4": {
              "bvps": 14777.12,
              "eps": 1594.05,
              "roe": 10.31,
              "roa": 1.4
            }
          },
          "bvps": 14611.86,
          "eps": 1414.51,
          "roe": 10.31,
          "roa": 1.4,
          "doanh_so": 749702486,
          "loi_nhuan_sau_thue": 22713467,
          "tai_san": 1578466002,
          "no_dai_han": 696788016,
          "von_chu_so_huu": 233911650,
          "roic": 2.4404722414502293,
          "effectiveness": 0.47495637223106946,
          "effciency": 3.029664089976087
        },
        "2014": {
          "quarter": {
            "q1": {},
            "q2": {},
            "q3": {},
            "q4": {
              "doanh_so": 619473785,
              "loi_nhuan_sau_thue": 34000272,
              "tai_san": 1255864594,
              "no_dai_han": 405803458,
              "von_chu_so_huu": 236557148,
              "roic": 5.293019478843944,
              "effectiveness": 0.49326478981857497,
              "effciency": 5.488573176668001,
              "bvps": 14736.25,
              "eps": 1744.64,
              "roe": 11.89,
              "roa": 1.98
            }
          },
          "bvps": 14736.25,
          "eps": 1744.64,
          "roe": 11.89,
          "roa": 1.98,
          "doanh_so": 834226543,
          "loi_nhuan_sau_thue": 41488817,
          "tai_san": 1246026031,
          "no_dai_han": 405803458,
          "von_chu_so_huu": 235902861,
          "roic": 6.4653901280968995,
          "effectiveness": 0.6695097231078634,
          "effciency": 4.973327371099963
        },
        "2015": {
          "quarter": {
            "q1": {},
            "q2": {
              "doanh_so": 91679880,
              "loi_nhuan_sau_thue": 10733578,
              "tai_san": 1188352611,
              "no_dai_han": 345759411,
              "von_chu_so_huu": 336157367,
              "roic": 1.5740304896853556,
              "effectiveness": 0.07714871760398732,
              "effciency": 11.707670210737623
            },
            "q3": {
              "doanh_so": 140567147,
              "loi_nhuan_sau_thue": 7169622,
              "tai_san": 1188784855,
              "no_dai_han": 353594999,
              "von_chu_so_huu": 343326990,
              "roic": 1.0287553145349242,
              "effectiveness": 0.11824439587094168,
              "effciency": 5.100496206272152
            },
            "q4": {
              "doanh_so": 130020896,
              "loi_nhuan_sau_thue": 20529867,
              "tai_san": 1173687476,
              "no_dai_han": 325653918,
              "von_chu_so_huu": 363790789,
              "roic": 2.9777394461888296,
              "effectiveness": 0.11077982738907576,
              "effciency": 15.78966737777288,
              "bvps": 15911.76,
              "eps": 1809.82,
              "roe": 9.68,
              "roa": 2.4
            }
          },
          "bvps": 22659.84,
          "eps": 1809.82,
          "roe": 9.68,
          "roa": 2.4,
          "luu_chuyen_tien_te": 30980723,
          "doanh_so": 505573479,
          "loi_nhuan_sau_thue": 43897040,
          "tai_san": 1170221956,
          "no_dai_han": 325653918,
          "von_chu_so_huu": 362746382,
          "roic": 6.376673572048124,
          "effectiveness": 0.4320321255363628,
          "effciency": 8.682623164258187,
          "productitivty": 0.705758816539794
        },
        "2016": {
          "quarter": {
            "q1": {
              "bvps": 15989.93,
              "eps": 2199.35,
              "roe": 10.01,
              "roa": 3.03,
              "luu_chuyen_tien_te": -2388157,
              "doanh_so": 60001773,
              "loi_nhuan_sau_thue": 1456473,
              "tai_san": 1103218346,
              "no_dai_han": 311281566,
              "von_chu_so_huu": 364202855,
              "roic": 0.21561903646035385,
              "effectiveness": 0.05438793981042081,
              "effciency": 2.4273832708243472,
              "productitivty": -1.6396850473712867
            },
            "q2": {
              "bvps": 16105.4,
              "eps": 2008.22,
              "roe": 8.93,
              "roa": 2.82,
              "luu_chuyen_tien_te": 22432737,
              "doanh_so": 76266183,
              "loi_nhuan_sau_thue": 4530931,
              "tai_san": 1097896199,
              "no_dai_han": 309087104,
              "von_chu_so_huu": 368943742,
              "roic": 0.6682485062043918,
              "effectiveness": 0.06946575010412255,
              "effciency": 5.940943707645628,
              "productitivty": 4.951021545020217
            },
            "q3": {
              "bvps": 15657.21,
              "eps": 1603.25,
              "roe": 7.05,
              "roa": 2.3,
              "luu_chuyen_tien_te": 12994938,
              "doanh_so": 90876063,
              "loi_nhuan_sau_thue": 25059,
              "tai_san": 1079108438,
              "no_dai_han": 292691369,
              "von_chu_so_huu": 360179506,
              "roic": 0.00383827812812143,
              "effectiveness": 0.08421402316937494,
              "effciency": 0.027574918160792244,
              "productitivty": 518.5736861008021
            },
            "q4": {
              "bvps": 16611.26,
              "eps": 1328.8,
              "roe": 5.75,
              "roa": 1.98,
              "luu_chuyen_tien_te": 56657932,
              "doanh_so": 122544476,
              "loi_nhuan_sau_thue": 15143762,
              "tai_san": 975229384,
              "no_dai_han": 253163946,
              "von_chu_so_huu": 375286404,
              "roic": 2.409699031912386,
              "effectiveness": 0.125657079257981,
              "effciency": 12.357767966627888,
              "productitivty": 3.741337984577412
            }
          },
          "bvps": 23532.81,
          "eps": 1328.8,
          "roe": 5.75,
          "roa": 1.98,
          "luu_chuyen_tien_te": 88119218,
          "doanh_so": 349581672,
          "loi_nhuan_sau_thue": 22561993,
          "tai_san": 977674068,
          "no_dai_han": 253252376,
          "von_chu_so_huu": 376721220,
          "roic": 3.5814188314013085,
          "effectiveness": 0.3575646357432076,
          "effciency": 6.4539976798325975,
          "productitivty": 3.90564867208318
        },
        "2017": {
          "quarter": {
            "q1": {
              "bvps": 16313.29,
              "eps": 849.91,
              "roe": 3.69,
              "roa": 1.31,
              "luu_chuyen_tien_te": -33793340,
              "doanh_so": 35562093,
              "loi_nhuan_sau_thue": -4409425,
              "effciency": -12.399228020690458,
              "productitivty": 7.663888148681518
            },
            "q2": {
              "bvps": 16258.17,
              "eps": 708.62,
              "roe": 3.07,
              "roa": 1.11,
              "luu_chuyen_tien_te": -4215500,
              "doanh_so": 49856702,
              "loi_nhuan_sau_thue": 1233020,
              "tai_san": 1032047296,
              "no_dai_han": 278238405,
              "von_chu_so_huu": 371785699,
              "roic": 0.18968835038769577,
              "effectiveness": 0.04830854379758968,
              "effciency": 2.473127885595,
              "productitivty": -3.4188415435272743
            },
            "q3": {
              "bvps": 16634.55,
              "eps": 985.72,
              "roe": 4.22,
              "roa": 1.55,
              "luu_chuyen_tien_te": -17040339,
              "doanh_so": 62089197,
              "loi_nhuan_sau_thue": 5696594,
              "tai_san": 1066635585,
              "no_dai_han": 277862631,
              "von_chu_so_huu": 377482294,
              "roic": 0.8692512572673086,
              "effectiveness": 0.058210318381605466,
              "effciency": 9.174855329502812,
              "productitivty": -2.991320603153393
            },
            "q4": {
              "luu_chuyen_tien_te": 25388628,
              "doanh_so": 37405888,
              "loi_nhuan_sau_thue": -2223953,
              "tai_san": 1030375715,
              "no_dai_han": 263190692,
              "von_chu_so_huu": 350297504,
              "roic": -0.3625095013238038,
              "effectiveness": 0.03630315374814516,
              "effciency": -5.945462382820587,
              "productitivty": -11.415991255210878,
              "bvps": 15881.15,
              "eps": 20.74,
              "roe": 0.09,
              "roa": 0.03
            }
          },
          "bvps": 21871.07,
          "eps": 20.74,
          "roe": 0.09,
          "roa": 0.03,
          "luu_chuyen_tien_te": -29619744,
          "doanh_so": 184913881,
          "loi_nhuan_sau_thue": 118148,
          "tai_san": 1030260815,
          "no_dai_han": 263190692,
          "von_chu_so_huu": 350119416,
          "roic": 0.019263990346625758,
          "effectiveness": 0.17948259150281282,
          "effciency": 0.0638935267385362,
          "productitivty": -250.70034194400245
        },
        "2018": {
          "quarter": {
            "q1": {
              "bvps": 16146.44,
              "eps": 595.23,
              "roe": 2.62,
              "roa": 0.91,
              "luu_chuyen_tien_te": 18124610,
              "doanh_so": 96746923,
              "loi_nhuan_sau_thue": 4224251,
              "tai_san": 1055335059,
              "no_dai_han": 303968336,
              "von_chu_so_huu": 354343667,
              "roic": 0.6416791704768597,
              "effectiveness": 0.0916741296282473,
              "effciency": 4.3662897682027575,
              "productitivty": 4.2906091517762555
            },
            "q2": {
              "bvps": 16055.66,
              "eps": 544.66,
              "roe": 2.43,
              "roa": 0.81,
              "luu_chuyen_tien_te": 57839181,
              "doanh_so": 27486237,
              "loi_nhuan_sau_thue": -117750,
              "tai_san": 1136768947,
              "no_dai_han": 354984675,
              "von_chu_so_huu": 352705671,
              "roic": -0.016638633078089212,
              "effectiveness": 0.024179264460502545,
              "effciency": -0.42839621880579726,
              "productitivty": -491.20323566878983
            },
            "q3": {
              "bvps": 16357.23,
              "eps": 444.59,
              "roe": 2.01,
              "roa": 0.65,
              "luu_chuyen_tien_te": 21273630,
              "doanh_so": 84010951,
              "loi_nhuan_sau_thue": 4630789,
              "tai_san": 1126879010,
              "no_dai_han": 315611930,
              "von_chu_so_huu": 356953547,
              "roic": 0.6885261224908218,
              "effectiveness": 0.07455188201615362,
              "effciency": 5.5121254370754595,
              "productitivty": 4.593953643752717
            },
            "q4": {
              "luu_chuyen_tien_te": 64815474,
              "doanh_so": 149557202,
              "loi_nhuan_sau_thue": 2720502,
              "tai_san": 1139163966,
              "no_dai_han": 352894255,
              "von_chu_so_huu": 333169782,
              "roic": 0.39653761941758797,
              "effectiveness": 0.1312868089789982,
              "effciency": 1.8190377752587268,
              "productitivty": 23.824821301362764,
              "bvps": 15524.55,
              "eps": 715.18,
              "roe": 3.35,
              "roa": 1.06
            }
          },
          "bvps": 20812.27,
          "eps": 715.18,
          "roe": 3.35,
          "roa": 1.06,
          "luu_chuyen_tien_te": 163194804,
          "doanh_so": 358081132,
          "loi_nhuan_sau_thue": 11448917,
          "tai_san": 1139471766,
          "no_dai_han": 352894255,
          "von_chu_so_huu": 333169782,
          "roic": 1.6687825600163328,
          "effectiveness": 0.31425186887868883,
          "effciency": 3.1972969187329308,
          "productitivty": 14.254169542848464
        },
        "2019": {
          "quarter": {
            "q1": {
              "bvps": 15534.97,
              "eps": 460.87,
              "roe": 2.14,
              "roa": 0.65,
              "luu_chuyen_tien_te": 15430265,
              "doanh_so": 9545042,
              "loi_nhuan_sau_thue": 166789,
              "tai_san": 1103318940,
              "no_dai_han": 381933324,
              "von_chu_so_huu": 333336571,
              "roic": 0.023318330767996324,
              "effectiveness": 0.0086512083260349,
              "effciency": 1.7473888538154152,
              "productitivty": 92.51368495524285
            },
            "q2": {
              "bvps": 15458.22,
              "eps": 473.58,
              "roe": 2.24,
              "roa": 0.68,
              "luu_chuyen_tien_te": 6509589,
              "doanh_so": 70214964,
              "loi_nhuan_sau_thue": 270512,
              "tai_san": 1099598341,
              "no_dai_han": 382164721,
              "von_chu_so_huu": 332107927,
              "roic": 0.037872372791741,
              "effectiveness": 0.06385510179666595,
              "effciency": 0.3852626058456713,
              "productitivty": 24.06395649730881
            },
            "q3": {
              "bvps": 15507.17,
              "eps": 246.2,
              "roe": 1.18,
              "roa": 0.36,
              "luu_chuyen_tien_te": -28078178,
              "doanh_so": 65937442,
              "loi_nhuan_sau_thue": 783502,
              "tai_san": 1097814421,
              "no_dai_han": 378527349,
              "von_chu_so_huu": 332891428,
              "roic": 0.11013231943412705,
              "effectiveness": 0.06006246660518226,
              "effciency": 1.1882505238829253,
              "productitivty": -35.83676621119027
            },
            "q4": {
              "luu_chuyen_tien_te": -45097705,
              "doanh_so": 201209334,
              "loi_nhuan_sau_thue": 8627929,
              "tai_san": 1099042747,
              "no_dai_han": 301356891,
              "von_chu_so_huu": 330858191,
              "roic": 1.3647142002221326,
              "effectiveness": 0.18307689537029445,
              "effciency": 4.288036160390054,
              "productitivty": -5.226944380279439,
              "bvps": 20672.03,
              "eps": 739.31,
              "roe": 3.56,
              "roa": 1.06
            }
          },
          "bvps": 20672.03,
          "eps": 739.31,
          "roe": 3.56,
          "roa": 1.06,
          "luu_chuyen_tien_te": -49724019,
          "doanh_so": 346906782,
          "loi_nhuan_sau_thue": 9848733,
          "tai_san": 1097801546,
          "no_dai_han": 301356891,
          "von_chu_so_huu": 330924857,
          "roic": 1.5576494230859879,
          "effectiveness": 0.3160013604134604,
          "effciency": 2.8390142571499224,
          "productitivty": -5.048773177219852
        },
        "2020": {
          "quarter": {
            "q1": {
              "bvps": 20706.1,
              "eps": 770.5,
              "roe": 3.72,
              "roa": 1.15,
              "luu_chuyen_tien_te": 70385934,
              "doanh_so": 67408929,
              "loi_nhuan_sau_thue": 665989,
              "tai_san": 999874094,
              "no_dai_han": 311777494,
              "von_chu_so_huu": 331470180,
              "roic": 0.10353539187457675,
              "effectiveness": 0.0674174172573372,
              "effciency": 0.9879833575163314,
              "productitivty": 105.68633115561968
            },
            "q2": {
              "bvps": 20638.95,
              "eps": 793.02,
              "roe": 3.83,
              "roa": 1.21,
              "luu_chuyen_tien_te": 7347912,
              "doanh_so": 90058018,
              "loi_nhuan_sau_thue": 631090,
              "tai_san": 1014669232,
              "no_dai_han": 304732666,
              "von_chu_so_huu": 330395299,
              "roic": 0.09936422812054892,
              "effectiveness": 0.08875603512928831,
              "effciency": 0.7007593704760413,
              "productitivty": 11.64320778335895
            },
            "q3": {
              "bvps": 20697.25,
              "eps": 806.16,
              "roe": 3.9,
              "roa": 1.23,
              "luu_chuyen_tien_te": 41512891,
              "doanh_so": 159799916,
              "loi_nhuan_sau_thue": 993901,
              "tai_san": 1066945898,
              "no_dai_han": 297123252,
              "von_chu_so_huu": 331328533,
              "roic": 0.15815071636720707,
              "effectiveness": 0.1497732137117228,
              "effciency": 0.62196590891825,
              "productitivty": 41.767631786264424
            },
            "q4": {
              "luu_chuyen_tien_te": -62721583,
              "doanh_so": 142994225,
              "loi_nhuan_sau_thue": 2213519,
              "tai_san": 1054668284,
              "no_dai_han": 266357052,
              "von_chu_so_huu": 321021799,
              "roic": 0.37684690148981886,
              "effectiveness": 0.13558217988472288,
              "effciency": 1.547977899107464,
              "productitivty": -28.335687653912164,
              "bvps": 20053.41,
              "eps": 298.26,
              "roe": 1.46,
              "roa": 0.44
            }
          },
          "bvps": 20053.41,
          "eps": 298.26,
          "roe": 1.46,
          "roa": 0.44,
          "luu_chuyen_tien_te": 56103468,
          "doanh_so": 460261088,
          "loi_nhuan_sau_thue": 4504500,
          "tai_san": 1054668284,
          "no_dai_han": 266357052,
          "von_chu_so_huu": 321021799,
          "roic": 0.76688154371428,
          "effectiveness": 0.43640364935824694,
          "effciency": 0.9786836466175477,
          "productitivty": 12.454982350982352
        },
        "2021": {
          "quarter": {
            "q1": {
              "bvps": 21922.85,
              "eps": 290.57,
              "roe": 1.43,
              "roa": 0.45,
              "luu_chuyen_tien_te": 28376129,
              "doanh_so": 72591210,
              "loi_nhuan_sau_thue": 397358,
              "tai_san": 990962808,
              "no_dai_han": 269290303,
              "von_chu_so_huu": 321352490,
              "roic": 0.06727551825050374,
              "effectiveness": 0.0732532133536943,
              "effciency": 0.5473913439381985,
              "productitivty": 71.41199875175535
            },
            "q2": {},
            "q3": {},
            "q4": {}
          }
        }
      }
    }
  ]
}