{
  "value": [
    {
      "code": "VMC",
      "url": "/hastc/VMC-cong-ty-co-phan-vimeco.chn",
      "company": "Công ty Cổ phần Vimeco",
      "price": 10,
      "stock_exchange": "HNX",
      "branch": "DOANH NGHIEP THONG THUONG",
      "data": {
        "2011": {
          "quarter": {
            "q1": {
              "luu_chuyen_tien_te": -34147075,
              "doanh_so": 175645969,
              "loi_nhuan_sau_thue": 3461300,
              "tai_san": 1068186585,
              "no_dai_han": 91431587,
              "von_chu_so_huu": 211251111,
              "roic": 1.143540751708246,
              "effectiveness": 0.16443379037567674,
              "effciency": 1.970611691065908,
              "productitivty": -9.865390171322913
            },
            "q2": {
              "luu_chuyen_tien_te": 39975941,
              "doanh_so": 222706661,
              "loi_nhuan_sau_thue": 3902915,
              "tai_san": 1056079107,
              "no_dai_han": 72652834,
              "von_chu_so_huu": 197879092,
              "roic": 1.4426818519009101,
              "effectiveness": 0.2108806618025443,
              "effciency": 1.7524913635160646,
              "productitivty": 10.242585605886882
            },
            "q3": {
              "luu_chuyen_tien_te": 16692430,
              "doanh_so": 259232004,
              "loi_nhuan_sau_thue": 6484395,
              "tai_san": 1004922503,
              "no_dai_han": 62447113,
              "von_chu_so_huu": 204070237,
              "roic": 2.433010458793771,
              "effectiveness": 0.25796218437353474,
              "effciency": 2.501386750071183,
              "productitivty": 2.5742463252161536
            },
            "q4": {
              "luu_chuyen_tien_te": -76429360,
              "doanh_so": 345858357,
              "loi_nhuan_sau_thue": 11132349,
              "tai_san": 1081953829,
              "no_dai_han": 53423178,
              "von_chu_so_huu": 213451086,
              "roic": 4.17138349466324,
              "effectiveness": 0.3196609205770462,
              "effciency": 3.2187595802405315,
              "productitivty": -6.865519577224896
            }
          },
          "bvps": 32611.51,
          "eps": 3838.7,
          "roe": 11.9,
          "roa": 2.3,
          "luu_chuyen_tien_te": 30260942,
          "doanh_so": 1003442991,
          "loi_nhuan_sau_thue": 24980959,
          "tai_san": 1086322447,
          "no_dai_han": 53313178,
          "von_chu_so_huu": 211974802,
          "roic": 9.416543863012565,
          "effectiveness": 0.9237063946999523,
          "effciency": 2.4895244895880686,
          "productitivty": 1.2113603004592417
        },
        "2012": {
          "quarter": {
            "q1": {
              "luu_chuyen_tien_te": -645085,
              "doanh_so": 155654807,
              "loi_nhuan_sau_thue": 3048698,
              "tai_san": 1019996797,
              "no_dai_han": 43337273,
              "von_chu_so_huu": 215678109,
              "roic": 1.177033570925143,
              "effectiveness": 0.15260323116485236,
              "effciency": 1.9586275931716006,
              "productitivty": -0.21159360487657355
            },
            "q2": {
              "luu_chuyen_tien_te": -14977608,
              "doanh_so": 279128355,
              "loi_nhuan_sau_thue": 7143642,
              "tai_san": 1014855432,
              "no_dai_han": 38048503,
              "von_chu_so_huu": 201034213,
              "roic": 2.9879374467203226,
              "effectiveness": 0.27504248013918103,
              "effciency": 2.55926776052544,
              "productitivty": -2.0966347417745737
            },
            "q3": {
              "bvps": 31304.69,
              "eps": 3524.87,
              "roe": 10.97,
              "roa": 2.21,
              "luu_chuyen_tien_te": -13332347,
              "doanh_so": 196781784,
              "loi_nhuan_sau_thue": 2953864,
              "tai_san": 1025162358,
              "no_dai_han": 52819167,
              "von_chu_so_huu": 205467190,
              "roic": 1.143639189583676,
              "effectiveness": 0.1919518234983809,
              "effciency": 1.5010860964651076,
              "productitivty": -4.5135277047284506
            },
            "q4": {
              "luu_chuyen_tien_te": 46944871,
              "doanh_so": 346761809,
              "loi_nhuan_sau_thue": -938888,
              "tai_san": 958895216,
              "no_dai_han": 16689075,
              "von_chu_so_huu": 203480476,
              "roic": -0.42643862229614116,
              "effectiveness": 0.36162638337743047,
              "effciency": -0.27075876743969807,
              "productitivty": -50.00050165727968,
              "bvps": 30995.33,
              "eps": 1652.56,
              "roe": 5.2,
              "roa": 1.05
            }
          },
          "bvps": 30995.33,
          "eps": 1652.56,
          "roe": 5.2,
          "roa": 1.05,
          "luu_chuyen_tien_te": 17989831,
          "doanh_so": 978487337,
          "loi_nhuan_sau_thue": 11709202,
          "tai_san": 952395208,
          "no_dai_han": 15439075,
          "von_chu_so_huu": 201469615,
          "roic": 5.398217102320797,
          "effectiveness": 1.0273963253708434,
          "effciency": 1.1966636212073942,
          "productitivty": 1.5363840336856431
        },
        "2013": {
          "quarter": {
            "q1": {
              "bvps": 31398.8,
              "eps": 1677.06,
              "roe": 5.36,
              "roa": 1.14,
              "luu_chuyen_tien_te": 60771909,
              "doanh_so": 192428717,
              "loi_nhuan_sau_thue": 2695986,
              "tai_san": 813845495,
              "no_dai_han": 9998575,
              "von_chu_so_huu": 204092200,
              "roic": 1.259272381072935,
              "effectiveness": 0.2364437945312949,
              "effciency": 1.4010310113952482,
              "productitivty": 22.541626328920106
            },
            "q2": {
              "bvps": 30270.9,
              "eps": 939.61,
              "roe": 3.02,
              "roa": 0.68,
              "luu_chuyen_tien_te": 13485709,
              "doanh_so": 132760749,
              "loi_nhuan_sau_thue": 1898722,
              "tai_san": 804627608,
              "no_dai_han": 9031432,
              "von_chu_so_huu": 196760851,
              "roic": 0.9226400389367371,
              "effectiveness": 0.1649965122747814,
              "effciency": 1.4301832539375023,
              "productitivty": 7.102518957488248
            },
            "q3": {
              "bvps": 30641.08,
              "eps": 795.81,
              "roe": 2.58,
              "roa": 0.62,
              "luu_chuyen_tien_te": -1930130,
              "doanh_so": 180185736,
              "loi_nhuan_sau_thue": 1906924,
              "tai_san": 766397216,
              "no_dai_han": 11641182,
              "von_chu_so_huu": 199167049,
              "roic": 0.9045775826466661,
              "effectiveness": 0.23510750331326882,
              "effciency": 1.0583101872170393,
              "productitivty": -1.0121693365860411
            },
            "q4": {
              "luu_chuyen_tien_te": 7423169,
              "doanh_so": 247234147,
              "loi_nhuan_sau_thue": 3654298,
              "tai_san": 828655252,
              "no_dai_han": 8907978,
              "von_chu_so_huu": 202531788,
              "roic": 1.728292680762804,
              "effectiveness": 0.2983558559525065,
              "effciency": 1.4780717163636785,
              "productitivty": 2.031352943848586,
              "bvps": 31055.86,
              "eps": 1455.98,
              "roe": 4.69,
              "roa": 1.06
            }
          },
          "bvps": 31055.86,
          "eps": 1455.98,
          "roe": 4.69,
          "roa": 1.06,
          "luu_chuyen_tien_te": 68122296,
          "doanh_so": 753976471,
          "loi_nhuan_sau_thue": 9898536,
          "tai_san": 828439101,
          "no_dai_han": 8322077,
          "von_chu_so_huu": 201863094,
          "roic": 4.7094359477910075,
          "effectiveness": 0.9101169537868059,
          "effciency": 1.3128441510743112,
          "productitivty": 6.882057710352319
        },
        "2014": {
          "quarter": {
            "q1": {
              "bvps": 31349.45,
              "eps": 1387.12,
              "roe": 4.5,
              "roa": 1.13,
              "luu_chuyen_tien_te": 8254238,
              "doanh_so": 117011326,
              "loi_nhuan_sau_thue": 1926745,
              "tai_san": 797373790,
              "no_dai_han": 10113828,
              "von_chu_so_huu": 203771412,
              "roic": 0.9008312121023404,
              "effectiveness": 0.14674588940276054,
              "effciency": 1.6466311987610498,
              "productitivty": 4.284032396606713
            },
            "q2": {
              "bvps": 30656.17,
              "eps": 1825.7,
              "roe": 5.9,
              "roa": 1.46,
              "luu_chuyen_tien_te": 25849579,
              "doanh_so": 191972532,
              "loi_nhuan_sau_thue": 4577704,
              "tai_san": 863131009,
              "no_dai_han": 7592458,
              "von_chu_so_huu": 199265083,
              "roic": 2.21297419367467,
              "effectiveness": 0.22241412948703365,
              "effciency": 2.3845619747308433,
              "productitivty": 5.646843701558685
            },
            "q3": {
              "bvps": 31266.8,
              "eps": 2129.43,
              "roe": 6.85,
              "roa": 1.61,
              "luu_chuyen_tien_te": 6501770,
              "doanh_so": 231944179,
              "loi_nhuan_sau_thue": 4025031,
              "tai_san": 939606436,
              "no_dai_han": 17273450,
              "von_chu_so_huu": 203234224,
              "roic": 1.8253473572987762,
              "effectiveness": 0.24685248005261642,
              "effciency": 1.7353446925693274,
              "productitivty": 1.615334142768093
            },
            "q4": {
              "luu_chuyen_tien_te": 62207907,
              "doanh_so": 347941378,
              "loi_nhuan_sau_thue": 8889348,
              "tai_san": 1049514605,
              "no_dai_han": 20646383,
              "von_chu_so_huu": 211763955,
              "roic": 3.8248505107376074,
              "effectiveness": 0.33152599910698716,
              "effciency": 2.554840718024632,
              "productitivty": 6.9980280893491855,
              "bvps": 32544.94,
              "eps": 2883.76,
              "roe": 9.07,
              "roa": 2
            }
          },
          "bvps": 33511.2,
          "eps": 3056.94,
          "roe": 9.47,
          "roa": 2.11,
          "luu_chuyen_tien_te": 106086733,
          "doanh_so": 888408696,
          "loi_nhuan_sau_thue": 20297996,
          "tai_san": 1051453705,
          "no_dai_han": 25627851,
          "von_chu_so_huu": 217822805,
          "roic": 8.337622224357448,
          "effectiveness": 0.8449337253512269,
          "effciency": 2.2847588155530616,
          "productitivty": 5.226463390770202
        },
        "2015": {
          "quarter": {
            "q1": {
              "bvps": 25132.04,
              "eps": 2902.83,
              "roe": 9.89,
              "roa": 2.19,
              "luu_chuyen_tien_te": -15389984,
              "doanh_so": 198484662,
              "loi_nhuan_sau_thue": 4797724,
              "tai_san": 1063454671,
              "no_dai_han": 118411677,
              "von_chu_so_huu": 251320416,
              "roic": 1.2976217349896104,
              "effectiveness": 0.1866413937637404,
              "effciency": 2.4171761947026416,
              "productitivty": -3.2077676831764395
            },
            "q2": {
              "bvps": 23888.36,
              "eps": 2848.09,
              "roe": 10.34,
              "roa": 2.25,
              "luu_chuyen_tien_te": -46496537,
              "doanh_so": 265828279,
              "loi_nhuan_sau_thue": 6285702,
              "tai_san": 1128083523,
              "no_dai_han": 92447997,
              "von_chu_so_huu": 243668593,
              "roic": 1.8700957307700878,
              "effectiveness": 0.2356459194555579,
              "effciency": 2.3645723561261893,
              "productitivty": -7.397190799054743
            },
            "q3": {
              "bvps": 24466.12,
              "eps": 2767.37,
              "roe": 10.6,
              "roa": 2.3,
              "luu_chuyen_tien_te": 3099342,
              "doanh_so": 290103582,
              "loi_nhuan_sau_thue": 5804574,
              "tai_san": 1166126077,
              "no_dai_han": 91870235,
              "von_chu_so_huu": 249473167,
              "roic": 1.7005086273792984,
              "effectiveness": 0.2487754863919401,
              "effciency": 2.000862574664797,
              "productitivty": 0.5339482277252388
            },
            "q4": {
              "luu_chuyen_tien_te": 145499307,
              "doanh_so": 317821832,
              "loi_nhuan_sau_thue": 7885407,
              "tai_san": 1320607577,
              "no_dai_han": 261127607,
              "von_chu_so_huu": 258484270,
              "roic": 1.5175571131142562,
              "effectiveness": 0.2406633412796177,
              "effciency": 2.481077826019202,
              "productitivty": 18.45171809140606,
              "bvps": 25302.87,
              "eps": 3699.22,
              "roe": 10.1,
              "roa": 2.03
            }
          },
          "bvps": 25819.51,
          "eps": 2404.5,
          "roe": 10.1,
          "roa": 2.03,
          "luu_chuyen_tien_te": -108141858,
          "doanh_so": 1072234127,
          "loi_nhuan_sau_thue": 24484207,
          "tai_san": 1322065328,
          "no_dai_han": 260027607,
          "von_chu_so_huu": 258195070,
          "roic": 4.724649863209287,
          "effectiveness": 0.8110296097259121,
          "effciency": 2.2834758177772496,
          "productitivty": -4.416800511448053
        },
        "2016": {
          "quarter": {
            "q1": {
              "bvps": 23681.19,
              "eps": 2727.67,
              "roe": 10.99,
              "roa": 2.12,
              "luu_chuyen_tien_te": 59530111,
              "doanh_so": 322128538,
              "loi_nhuan_sau_thue": 7299411,
              "tai_san": 1539741836,
              "no_dai_han": 478398292,
              "von_chu_so_huu": 241545501,
              "roic": 1.0138862326437197,
              "effectiveness": 0.20920944697900642,
              "effciency": 2.265993272536443,
              "productitivty": 8.155467749384163
            },
            "q2": {
              "bvps": 24879.7,
              "eps": 3045.88,
              "roe": 12.15,
              "roa": 2.07,
              "luu_chuyen_tien_te": 148087479,
              "doanh_so": 405395739,
              "loi_nhuan_sau_thue": 9932639,
              "tai_san": 1849371979,
              "no_dai_han": 709466455,
              "von_chu_so_huu": 253605970,
              "roic": 1.0313491220559035,
              "effectiveness": 0.21920724635354713,
              "effciency": 2.450109373251207,
              "productitivty": 14.909177611307529
            },
            "q3": {
              "bvps": 25319.42,
              "eps": 2805.39,
              "roe": 11.09,
              "roa": 1.66,
              "luu_chuyen_tien_te": 86846277,
              "doanh_so": 387297561,
              "loi_nhuan_sau_thue": 3434414,
              "tai_san": 2053664262,
              "no_dai_han": 872012793,
              "von_chu_so_huu": 258064829,
              "roic": 0.3039095663111892,
              "effectiveness": 0.1885885478782315,
              "effciency": 0.8867636530249153,
              "productitivty": 25.287072845615
            },
            "q4": {
              "luu_chuyen_tien_te": 224628126,
              "doanh_so": 337396698,
              "loi_nhuan_sau_thue": 7224189,
              "tai_san": 2278460984,
              "no_dai_han": 958107621,
              "von_chu_so_huu": 265342768,
              "roic": 0.5904766605129586,
              "effectiveness": 0.1480809635843209,
              "effciency": 2.14115580941459,
              "productitivty": 31.093888324350317,
              "bvps": 24519.65,
              "eps": 2854.97,
              "roe": 11.23,
              "roa": 1.59
            }
          },
          "bvps": 25033.71,
          "eps": 2854.97,
          "roe": 11.23,
          "roa": 1.59,
          "luu_chuyen_tien_te": 335086806,
          "doanh_so": 1452568489,
          "loi_nhuan_sau_thue": 28963192,
          "tai_san": 2277530860,
          "no_dai_han": 957967127,
          "von_chu_so_huu": 250337111,
          "roic": 2.397011538082514,
          "effectiveness": 0.6377821326205871,
          "effciency": 1.99392952685758,
          "productitivty": 11.569401811789254
        },
        "2017": {
          "quarter": {
            "q1": {
              "bvps": 25055.2,
              "eps": 2521.36,
              "roe": 9.76,
              "roa": 1.2,
              "luu_chuyen_tien_te": -67582799,
              "doanh_so": 289888754,
              "loi_nhuan_sau_thue": 5508235,
              "tai_san": 2193321250,
              "no_dai_han": 1002104156,
              "von_chu_so_huu": 255845347,
              "roic": 0.4378740948554594,
              "effectiveness": 0.13216885305789108,
              "effciency": 1.9001202785534757,
              "productitivty": -12.269410981920705
            },
            "q2": {
              "bvps": 24432.24,
              "eps": 2374.94,
              "roe": 9.24,
              "roa": 1.08,
              "luu_chuyen_tien_te": -28568120,
              "doanh_so": 283521325,
              "loi_nhuan_sau_thue": 8026036,
              "tai_san": 2307200966,
              "no_dai_han": 57129269,
              "von_chu_so_huu": 249161272,
              "roic": 2.6203995636940025,
              "effectiveness": 0.12288540494655809,
              "effciency": 2.830840325679206,
              "productitivty": -3.5594308323560973
            },
            "q3": {
              "bvps": 24935.43,
              "eps": 2644.86,
              "roe": 10.33,
              "roa": 1.16,
              "luu_chuyen_tien_te": -44718010,
              "doanh_so": 227456315,
              "loi_nhuan_sau_thue": 6102957,
              "tai_san": 2368141352,
              "no_dai_han": 49925098,
              "von_chu_so_huu": 254224229,
              "roic": 2.0065660049939877,
              "effectiveness": 0.09604845369889052,
              "effciency": 2.68313368217541,
              "productitivty": -7.327269387609974
            },
            "q4": {
              "luu_chuyen_tien_te": 127164995,
              "doanh_so": 1468763286,
              "loi_nhuan_sau_thue": 211412646,
              "tai_san": 1983466504,
              "no_dai_han": 51759616,
              "von_chu_so_huu": 464870509,
              "roic": 40.92147084918828,
              "effectiveness": 0.7405031963171484,
              "effciency": 14.393922289258528,
              "productitivty": 0.601501364303439,
              "bvps": 45998.91,
              "eps": 23089.56,
              "roe": 64.54,
              "roa": 10.69
            }
          },
          "bvps": 46516.81,
          "eps": 23089.56,
          "roe": 64.54,
          "roa": 10.69,
          "luu_chuyen_tien_te": -21094505,
          "doanh_so": 2269725706,
          "loi_nhuan_sau_thue": 231347497,
          "tai_san": 2044182042,
          "no_dai_han": 49126185,
          "von_chu_so_huu": 465168132,
          "roic": 44.98348306656478,
          "effectiveness": 1.110334431751162,
          "effciency": 10.192751326225673,
          "productitivty": -0.09118103836671292
        },
        "2018": {
          "quarter": {
            "q1": {
              "bvps": 24989.3,
              "eps": 24527.52,
              "roe": 80.2,
              "roa": 11.75,
              "luu_chuyen_tien_te": -29563771,
              "doanh_so": 286773481,
              "loi_nhuan_sau_thue": 19706665,
              "tai_san": 1690538327,
              "no_dai_han": 33894239,
              "von_chu_so_huu": 255081465,
              "roic": 6.819488533887263,
              "effectiveness": 0.16963441551124325,
              "effciency": 6.871857513212667,
              "productitivty": -1.5001914834397398
            },
            "q2": {
              "bvps": 26903.12,
              "eps": 21225.57,
              "roe": 82.22,
              "roa": 13.66,
              "luu_chuyen_tien_te": -55024612,
              "doanh_so": 416958646,
              "loi_nhuan_sau_thue": 19470034,
              "tai_san": 1470140621,
              "no_dai_han": 38027140,
              "von_chu_so_huu": 273634786,
              "roic": 6.247164756339214,
              "effectiveness": 0.28361820634299717,
              "effciency": 4.669535980793644,
              "productitivty": -2.826117920492589
            },
            "q3": {
              "bvps": 19846.35,
              "eps": 21499.53,
              "roe": 85.97,
              "roa": 17.07,
              "luu_chuyen_tien_te": 368851248,
              "doanh_so": 398037637,
              "loi_nhuan_sau_thue": 27578745,
              "tai_san": 1377039858,
              "no_dai_han": 22903233,
              "von_chu_so_huu": 301213531,
              "roic": 8.508891875768573,
              "effectiveness": 0.2890530979822953,
              "effciency": 6.928677701902848,
              "productitivty": 13.374475452019299
            },
            "q4": {
              "luu_chuyen_tien_te": 56785930,
              "doanh_so": 459851018,
              "loi_nhuan_sau_thue": 21671565,
              "tai_san": 1595262096,
              "no_dai_han": 47900835,
              "von_chu_so_huu": 423291342,
              "roic": 4.599304924368471,
              "effectiveness": 0.2882604803016645,
              "effciency": 4.712736114895368,
              "productitivty": 2.620296688310235,
              "bvps": 20968.88,
              "eps": 4513.25,
              "roe": 20.33,
              "roa": 4.96
            }
          },
          "bvps": 21210.61,
          "eps": 4580.2,
          "roe": 20.6,
          "roa": 5.04,
          "luu_chuyen_tien_te": -76965019,
          "doanh_so": 1570265138,
          "loi_nhuan_sau_thue": 90372519,
          "tai_san": 1589735643,
          "no_dai_han": 89835625,
          "von_chu_so_huu": 424212143,
          "roic": 17.58056831014195,
          "effectiveness": 0.9877523630512196,
          "effciency": 5.7552394696289815,
          "productitivty": -0.8516418470088235
        },
        "2019": {
          "quarter": {
            "q1": {
              "bvps": 18087.82,
              "eps": 4557.61,
              "roe": 20.1,
              "roa": 4.6,
              "luu_chuyen_tien_te": -17645140,
              "doanh_so": 215224791,
              "loi_nhuan_sau_thue": 4370756,
              "tai_san": 1506907106,
              "no_dai_han": 85411011,
              "von_chu_so_huu": 365022608,
              "roic": 0.9703440897025939,
              "effectiveness": 0.14282551999592202,
              "effciency": 2.0307864998693392,
              "productitivty": -4.037091066167958
            },
            "q2": {
              "bvps": 18253.94,
              "eps": 3230.92,
              "roe": 15.56,
              "roa": 3.82,
              "luu_chuyen_tien_te": -3065944,
              "doanh_so": 323324068,
              "loi_nhuan_sau_thue": 1561319,
              "tai_san": 1458105426,
              "no_dai_han": 79846917,
              "von_chu_so_huu": 368144217,
              "roic": 0.3485156025431521,
              "effectiveness": 0.22174258612216424,
              "effciency": 0.48289600265699983,
              "productitivty": -1.9636883942358994
            },
            "q3": {
              "bvps": 18257.27,
              "eps": 1436.65,
              "roe": 7.58,
              "roa": 1.95,
              "luu_chuyen_tien_te": 87935973,
              "doanh_so": 276357627,
              "loi_nhuan_sau_thue": -543477,
              "tai_san": 1357678205,
              "no_dai_han": 77156419,
              "von_chu_so_huu": 367599740,
              "roic": -0.12219662145252046,
              "effectiveness": 0.2035516413110572,
              "effciency": -0.1966571380351301,
              "productitivty": -161.80256570195243
            },
            "q4": {
              "luu_chuyen_tien_te": 59959554,
              "doanh_so": 337169516,
              "loi_nhuan_sau_thue": 9086322,
              "tai_san": 1340559395,
              "no_dai_han": 70832670,
              "von_chu_so_huu": 376687062,
              "roic": 2.0303734897660335,
              "effectiveness": 0.2515140450005947,
              "effciency": 2.6948824163569993,
              "productitivty": 6.59888060317475,
              "bvps": 18501.83,
              "eps": 478.82,
              "roe": 2.41,
              "roa": 0.66
            }
          },
          "bvps": 18501.83,
          "eps": 478.82,
          "roe": 2.41,
          "roa": 0.66,
          "luu_chuyen_tien_te": 50909145,
          "doanh_so": 1156570476,
          "loi_nhuan_sau_thue": 7824529,
          "tai_san": 1320073646,
          "no_dai_han": 71194442,
          "von_chu_so_huu": 370036672,
          "roic": 1.7733402635789641,
          "effectiveness": 0.8761408725221986,
          "effciency": 0.6765285092752099,
          "productitivty": 6.506352650747412
        },
        "2020": {
          "quarter": {
            "q1": {
              "bvps": 18528.39,
              "eps": 527.84,
              "roe": 2.85,
              "roa": 0.79,
              "luu_chuyen_tien_te": -9997456,
              "doanh_so": 96677806,
              "loi_nhuan_sau_thue": 531153,
              "tai_san": 1159868746,
              "no_dai_han": 67009506,
              "von_chu_so_huu": 370567826,
              "roic": 0.12138494413600016,
              "effectiveness": 0.08335236752728227,
              "effciency": 0.5494053102529034,
              "productitivty": -18.822177414040777
            },
            "q2": {
              "bvps": 17629.24,
              "eps": 522.79,
              "roe": 2.85,
              "roa": 0.84,
              "luu_chuyen_tien_te": 21619490,
              "doanh_so": 273973414,
              "loi_nhuan_sau_thue": 16919,
              "tai_san": 1111975571,
              "no_dai_han": 64664181,
              "von_chu_so_huu": 352584744,
              "roic": 0.004054893610570716,
              "effectiveness": 0.2463843821259631,
              "effciency": 0.006175416713973568,
              "productitivty": 1277.8231573970093
            },
            "q3": {
              "bvps": 17630.39,
              "eps": 540.75,
              "roe": 2.98,
              "roa": 0.92,
              "luu_chuyen_tien_te": -19516115,
              "doanh_so": 122763662,
              "loi_nhuan_sau_thue": 23143,
              "tai_san": 1077246164,
              "no_dai_han": 61052077,
              "von_chu_so_huu": 352607887,
              "roic": 0.0055946917792605135,
              "effectiveness": 0.1139606397335939,
              "effciency": 0.018851669641461167,
              "productitivty": -843.2837142980599
            },
            "q4": {
              "luu_chuyen_tien_te": -17320456,
              "doanh_so": 148024625,
              "loi_nhuan_sau_thue": 3267029,
              "tai_san": 1071632553,
              "no_dai_han": 44500407,
              "von_chu_so_huu": 355874916,
              "roic": 0.8159915989627562,
              "effectiveness": 0.13813001908686887,
              "effciency": 2.2070848009241706,
              "productitivty": -5.30159236419389,
              "bvps": 17772.19,
              "eps": 166.43,
              "roe": 0.92,
              "roa": 0.28
            }
          },
          "bvps": 17772.19,
          "eps": 166.43,
          "roe": 0.92,
          "roa": 0.28,
          "luu_chuyen_tien_te": -22342409,
          "doanh_so": 642882780,
          "loi_nhuan_sau_thue": 3407060,
          "tai_san": 1069697608,
          "no_dai_han": 42975311,
          "von_chu_so_huu": 355443733,
          "roic": 0.8551448660169969,
          "effectiveness": 0.6009948748057778,
          "effciency": 0.5299659760679855,
          "productitivty": -6.557679935193392
        },
        "2021": {
          "quarter": {
            "q1": {
              "bvps": 17416.28,
              "eps": 287.08,
              "roe": 1.63,
              "roa": 0.53,
              "luu_chuyen_tien_te": 30971101,
              "doanh_so": 133161668,
              "loi_nhuan_sau_thue": 2881944,
              "tai_san": 1083343187,
              "no_dai_han": 45018360,
              "von_chu_so_huu": 348325676,
              "roic": 0.7326776908344939,
              "effectiveness": 0.12291734475088363,
              "effciency": 2.1642444430780188,
              "productitivty": 10.746600558511894
            },
            "q2": {},
            "q3": {},
            "q4": {}
          }
        }
      }
    }
  ]
}